clint/__init__.py
clint/arguments.py
clint/eng.py
clint/packages/__init__.py
clint/packages/appdirs.py
clint/packages/colorama/__init__.py
clint/packages/colorama/ansi.py
clint/packages/colorama/ansitowin32.py
clint/packages/colorama/initialise.py
clint/packages/colorama/win32.py
clint/packages/colorama/winterm.py
clint/packages/ordereddict.py
clint/pipes.py
clint/resources.py
clint/textui/__init__.py
clint/textui/colored.py
clint/textui/cols.py
clint/textui/core.py
clint/textui/formatters.py
clint/textui/progress.py
clint/textui/prompt.py
clint/textui/validators.py
clint/utils.py
core.py
functions.py
readme.md
dev_gossip-0.3.0.dist-info/entry_points.txt
dev_gossip-0.3.0.dist-info/WHEEL
dev_gossip-0.3.0.dist-info/METADATA
dev_gossip-0.3.0.dist-info/RECORD
