Metadata-Version: 2.1
Name: dev-gossip
Version: 0.3.0
Summary: 
Author: shols232
Requires-Python: >=3.7,<4.0
Classifier: Programming Language :: Python :: 3
Classifier: Programming Language :: Python :: 3.7
Classifier: Programming Language :: Python :: 3.8
